odoo/addons/l10n_it_vat_payability/README.rst
odoo/addons/l10n_it_vat_payability/__init__.py
odoo/addons/l10n_it_vat_payability/__manifest__.py
odoo/addons/l10n_it_vat_payability/i18n/es_AR.po
odoo/addons/l10n_it_vat_payability/i18n/it.po
odoo/addons/l10n_it_vat_payability/i18n/l10n_it_vat_payability.pot
odoo/addons/l10n_it_vat_payability/models/__init__.py
odoo/addons/l10n_it_vat_payability/models/account.py
odoo/addons/l10n_it_vat_payability/readme/CONTRIBUTORS.rst
odoo/addons/l10n_it_vat_payability/readme/DESCRIPTION.rst
odoo/addons/l10n_it_vat_payability/static/description/icon.png
odoo/addons/l10n_it_vat_payability/static/description/index.html
odoo/addons/l10n_it_vat_payability/views/account_view.xml
odoo14_addon_l10n_it_vat_payability-14.0.1.0.2.dist-info/METADATA
odoo14_addon_l10n_it_vat_payability-14.0.1.0.2.dist-info/WHEEL
odoo14_addon_l10n_it_vat_payability-14.0.1.0.2.dist-info/top_level.txt
odoo14_addon_l10n_it_vat_payability-14.0.1.0.2.dist-info/RECORD
