Metadata-Version: 2.1
Name: odoo14-addon-l10n-it-vat-payability
Version: 14.0.1.0.2
Summary: ITA - Esigibilità IVA
Home-page: https://github.com/OCA/l10n-italy
Author: Openforce di Camilli Alessandro, Odoo Community Association (OCA)
Author-email: support@odoo-community.org
License: LGPL-3
Platform: UNKNOWN
Classifier: Programming Language :: Python
Classifier: Framework :: Odoo
Classifier: License :: OSI Approved :: GNU Lesser General Public License v3 (LGPLv3)
Classifier: Development Status :: 4 - Beta
Requires-Python: >=3.6
Requires-Dist: odoo (<14.1dev,>=14.0a)
Requires-Dist: openupgradelib
